gedhtml/__init__.py
gedhtml/__main__.py
gedhtml/describe.py
gedhtml/family_tree.py
gedhtml/file.py
gedhtml/html_template.py
gedhtml/language.py
gedhtml/pedigree.py
gedhtml/utils.py
gedhtml/webpage.py
gedhtml-0.0.3.dist-info/LICENSE
gedhtml-0.0.3.dist-info/METADATA
gedhtml-0.0.3.dist-info/WHEEL
gedhtml-0.0.3.dist-info/RECORD
